{"achievement.openInventory":66,"stat.useItem.46":212,"stat.killEntity.Sheep":1,"stat.damageDealt":110,"stat.useItem.3":12,"achievement.exploreAllBiomes":{"value":0,"progress":["Forest","Taiga","TaigaHills","Beach","River"]},"stat.useItem.259":21,"stat.useItem.69":3,"stat.flyOneCm":98424,"stat.drop":2,"stat.useItem.4":3,"stat.playOneMinute":342138,"stat.useItem.154":15,"stat.killEntity.Creeper":1,"stat.jump":64,"stat.useItem.1":2,"stat.swimOneCm":1198,"stat.useItem.389":1,"stat.mobKills":3,"stat.walkOneCm":21273,"stat.useItem.7":1}