{"stat.damageDealt":50,"stat.useItem.3":51,"achievement.exploreAllBiomes":{"value":0,"progress":["Ice Plains","FrozenRiver","Ice Mountains","River","Cold Taiga"]},"stat.mineBlock.31":9,"stat.useItem.46":2,"achievement.openInventory":125,"stat.useItem.270":1,"stat.fallOneCm":8559,"stat.flyOneCm":121619,"stat.useItem.8":1,"stat.useItem.78":79,"stat.useItem.10":2,"stat.drop":27,"stat.damageTaken":-2147479739,"stat.useItem.80":1,"stat.playOneMinute":154094,"stat.mineBlock.15":1,"stat.diveOneCm":1938,"stat.useItem.15":1,"stat.mineBlock.79":2,"stat.mineBlock.3":13,"stat.deaths":4,"stat.jump":303,"stat.useItem.1":8,"stat.swimOneCm":21953,"stat.useItem.389":4,"stat.entityKilledBy.Zombie":1,"stat.useItem.137":4,"stat.walkOneCm":109870,"stat.useItem.77":3,"stat.useItem.257":12}